toothpyck/__init__.py
toothpyck/fake_data.py
toothpyck/test_convert_name.py
toothpyck-0.0.3.dist-info/LICENSE
toothpyck-0.0.3.dist-info/METADATA
toothpyck-0.0.3.dist-info/WHEEL
toothpyck-0.0.3.dist-info/top_level.txt
toothpyck-0.0.3.dist-info/RECORD
