Metadata-Version: 2.1
Name: toothpyck
Version: 0.0.3
Summary: Fake data for adwords testing.
Home-page: https://github.com/thorwhalen/newut/tree/master/toothpyck
Author: Thor Whalen
License: mit
Platform: any
License-File: LICENSE
